demo/__init__.py
demo/qram_sample.py
demo/qucat_test.py
qucat_cover/__init__.py
qucat_cover/executing.py
qucat_cover/generating.py
qucat_cover/qucat_run.py
qucat_cover_gpu-1.1.0.dist-info/LICENSE.py
qucat_cover_gpu-1.1.0.dist-info/METADATA
qucat_cover_gpu-1.1.0.dist-info/WHEEL
qucat_cover_gpu-1.1.0.dist-info/entry_points.txt
qucat_cover_gpu-1.1.0.dist-info/top_level.txt
qucat_cover_gpu-1.1.0.dist-info/RECORD
