Metadata-Version: 2.1
Name: qucat_cover_gpu
Version: 1.1.0
Summary: QuCAT: A Combinatorial Testing Tool for Quantum Software
Home-page: https://github.com/Simula-COMPLEX/qucat-tool/
Author: Xinyi Wang
Author-email: xinyi@simula.no
Classifier: Programming Language :: Python :: 3
Classifier: License :: OSI Approved :: MIT License
Classifier: Operating System :: OS Independent
Requires-Python: >=3.8
License-File: LICENSE.py
Requires-Dist: qiskit ==1.2.1
Requires-Dist: qiskit-aer-gpu ==0.15.1
